isogroup/__init__.py
isogroup/__main__.py
isogroup/base/__init__.py
isogroup/base/cluster.py
isogroup/base/database.py
isogroup/base/experiment.py
isogroup/base/feature.py
isogroup/base/io.py
isogroup/base/misc.py
isogroup/base/sample.py
isogroup/base/targeted_experiment.py
isogroup/base/untargeted_experiment.py
isogroup/ui/__init__.py
isogroup/ui/cli.py
isogroup-0.2.0.dist-info/licenses/LICENSE
isogroup-0.2.0.dist-info/METADATA
isogroup-0.2.0.dist-info/WHEEL
isogroup-0.2.0.dist-info/entry_points.txt
isogroup-0.2.0.dist-info/top_level.txt
isogroup-0.2.0.dist-info/RECORD
